openinference/instrumentation/pipecat/__init__.py
openinference/instrumentation/pipecat/_attributes.py
openinference/instrumentation/pipecat/_observer.py
openinference/instrumentation/pipecat/package.py
openinference/instrumentation/pipecat/version.py
openinference_instrumentation_pipecat-0.1.1.dist-info/METADATA
openinference_instrumentation_pipecat-0.1.1.dist-info/WHEEL
openinference_instrumentation_pipecat-0.1.1.dist-info/entry_points.txt
openinference_instrumentation_pipecat-0.1.1.dist-info/licenses/LICENSE
openinference_instrumentation_pipecat-0.1.1.dist-info/RECORD
